alchemyml/_CRUD_classes.py
alchemyml/__init__.py
alchemyml/_dict_urlData.py
alchemyml/_manual_ops.py
alchemyml/_request_handler.py
alchemyml/_version.py
alchemyml-0.1.36.dist-info/LICENSE
alchemyml-0.1.36.dist-info/METADATA
alchemyml-0.1.36.dist-info/WHEEL
alchemyml-0.1.36.dist-info/top_level.txt
alchemyml-0.1.36.dist-info/RECORD
