Metadata-Version: 2.1
Name: alchemyml
Version: 0.1.36
Summary: AlchemyML API package
Home-page: https://github.com/alchemyml/alchemyml
Author: Alchemy Machine Learning, S. L.
Author-email: admin@alchemyml.com
License: UNKNOWN
Platform: UNKNOWN
Classifier: Programming Language :: Python :: 3
Classifier: License :: OSI Approved :: MIT License
Classifier: Operating System :: OS Independent
Requires-Python: >=3.6
